network_scanner_kbk/__init__.py
network_scanner_kbk/example.py
network_scanner_kbk/network_scanner.py
network_scanner_kbk/ns_logger.py
network_scanner_kbk/tests/test_network_scanner.py
network_scanner_kbk-0.0.23.dist-info/LICENSE
network_scanner_kbk-0.0.23.dist-info/METADATA
network_scanner_kbk-0.0.23.dist-info/WHEEL
network_scanner_kbk-0.0.23.dist-info/top_level.txt
network_scanner_kbk-0.0.23.dist-info/RECORD
