Metadata-Version: 2.1
Name: network-scanner-kbk
Version: 0.0.23
Summary: Project to scan and gather connectivity information on small networks
Home-page: https://github.com/kbriankulig/network-scanner
Download-URL: 
Author: Brian Kulig
Author-email: kbriankulig@gmail.com
License: MIT License
License-File: LICENSE
